stablehash/__init__.py
stablehash/__init__test.py
stablehash/_tokenize.py
stablehash/py.typed
stablehash-0.2.4.dist-info/METADATA
stablehash-0.2.4.dist-info/WHEEL
stablehash-0.2.4.dist-info/licenses/LICENSE
stablehash-0.2.4.dist-info/RECORD
