Metadata-Version: 2.4
Name: stablehash
Version: 0.2.4
Summary: Stable hashing of Python data structures across separate processes and platforms.
Project-URL: Repository, https://github.com/NiklasRosenstein/python-stablehash
Project-URL: Issues, https://github.com/NiklasRosenstein/python-stablehash/issues
Author-email: Niklas Rosenstein <rosensteinniklas@gmail.com>
License: MIT
License-File: LICENSE
Keywords: dataclasses,hash,hashlib,python hashing,stable hash
Classifier: Development Status :: 5 - Production/Stable
Classifier: Intended Audience :: Developers
Classifier: License :: OSI Approved :: MIT License
Classifier: Programming Language :: Python
Classifier: Programming Language :: Python :: 3
Classifier: Programming Language :: Python :: 3.10
Classifier: Programming Language :: Python :: 3.11
Classifier: Programming Language :: Python :: 3.12
Classifier: Programming Language :: Python :: 3.13
Classifier: Topic :: Software Development :: Libraries
Classifier: Topic :: Software Development :: Libraries :: Python Modules
Classifier: Topic :: Utilities
Requires-Python: >=3.10
